xiTest/__init__.py
xiTest/caculate_site.py
xiTest/deal_fasta.py
xiTest/rename_fa.py
xiTest/run.tools_single.other.py
xiTest/run.tools_single.py
xiTest/run.tools_single_noPlot.py
xiTest/run.tools_single_noPlot_other.py
xiTest-0.2.dist-info/LICENSE
xiTest-0.2.dist-info/METADATA
xiTest-0.2.dist-info/WHEEL
xiTest-0.2.dist-info/top_level.txt
xiTest-0.2.dist-info/RECORD
