Metadata-Version: 2.1
Name: xiTest
Version: 0.2
Summary: call snp and indel in ncov
Home-page: UNKNOWN
Author: Liang Qian
Author-email: qliang77@126.com
License: MIT
Keywords: SOME,MEANINGFULL,KEYWORDS
Platform: UNKNOWN
Classifier: Development Status :: 3 - Alpha
Classifier: Intended Audience :: Developers
Classifier: Topic :: Software Development :: Build Tools
Classifier: License :: OSI Approved :: MIT License
Classifier: Programming Language :: Python :: 3
Classifier: Programming Language :: Python :: 3.4
Classifier: Programming Language :: Python :: 3.5
Classifier: Programming Language :: Python :: 3.6
Classifier: Programming Language :: Python :: 3.7
Classifier: Programming Language :: Python :: 3.8
License-File: LICENSE
Requires-Dist: biopython (==1.78)
Requires-Dist: svgwrite (==1.4.1)
